declarai/__init__.py
declarai/_base.py
declarai/chat.py
declarai/core/__init__.py
declarai/core/core_settings.py
declarai/declarai.py
declarai/evals/README.md
declarai/evals/__init__.py
declarai/evals/evaluator.py
declarai/evals/extraction/__init__.py
declarai/evals/extraction/multiple_value.py
declarai/evals/extraction/multiple_value_multi_types.py
declarai/evals/extraction/single_value.py
declarai/evals/extraction/single_value_multi_types.py
declarai/evals/generation/__init__.py
declarai/evals/generation/structured_open_ended.py
declarai/evals/generation/structured_strict_complex.py
declarai/evals/generation/unstructured_long_form.py
declarai/evals/generation/unstructured_short_form.py
declarai/evals/logical_tasks/__init__.py
declarai/evals/logical_tasks/sequence.py
declarai/evals/manipulation/__init__.py
declarai/evals/manipulation/data_manipulation_structured.py
declarai/evals/metadata_significance/__init__.py
declarai/evals/metadata_significance/simple_task_significance.py
declarai/evals/providers/__init__.py
declarai/evals/providers/openai.py
declarai/evals/runner.py
declarai/memory/__init__.py
declarai/memory/base.py
declarai/memory/file.py
declarai/memory/in_memory.py
declarai/memory/mongodb.py
declarai/memory/postgres.py
declarai/memory/redis.py
declarai/middleware/__init__.py
declarai/middleware/base.py
declarai/middleware/internal/__init__.py
declarai/middleware/internal/log_middleware.py
declarai/middleware/third_party/__init__.py
declarai/middleware/third_party/wandb_monitor.py
declarai/operators/__init__.py
declarai/operators/llm.py
declarai/operators/message.py
declarai/operators/openai_operators/__init__.py
declarai/operators/openai_operators/chat_operator.py
declarai/operators/openai_operators/openai_llm.py
declarai/operators/openai_operators/settings.py
declarai/operators/openai_operators/task_operator.py
declarai/operators/operator.py
declarai/operators/registry.py
declarai/operators/templates/__init__.py
declarai-0.1.13.dist-info/LICENSE
declarai-0.1.13.dist-info/METADATA
declarai-0.1.13.dist-info/WHEEL
declarai-0.1.13.dist-info/RECORD
