Metadata-Version: 2.1
Name: declarai
Version: 0.1.13
Summary: Declarai, turning Python code into LLM tasks, easy to use, and production-ready.
Author: Aviv Almashanu
Author-email: avivex1000@gmail.com
Requires-Python: >=3.8,<4.0
Classifier: Programming Language :: Python :: 3
Classifier: Programming Language :: Python :: 3.8
Classifier: Programming Language :: Python :: 3.9
Classifier: Programming Language :: Python :: 3.10
Classifier: Programming Language :: Python :: 3.11
Provides-Extra: mongo
Provides-Extra: postgresql
Provides-Extra: redis
Provides-Extra: wandb
Requires-Dist: jinja2 (>=3.1.2,<4.0.0)
Requires-Dist: jsonref (>=1.1.0,<2.0.0)
Requires-Dist: openai (>=0.27.8,<0.28.0)
Requires-Dist: pydantic (>=1.8.2,<2.0.0)
Requires-Dist: wandb (>=0.15.8,<0.16.0) ; extra == "wandb"
